tp4/verilog/fpga_tp4/src/mac_unit.v
module mac_unit (
    input  wire               clk,
    input  wire               rst_n,
    input  wire signed [15:0] a,
    input  wire signed [15:0] b,
    input  wire               mac_en,
    input  wire               clear_acc,
    output reg  signed [31:0] acc,
    output reg                overflow
);
    wire signed [31:0] product = a * b;
    wire signed [32:0] acc_ext     = {acc[31], acc};
    wire signed [32:0] product_ext = {product[31], product};
    wire signed [33:0] sum_ext     = acc_ext + product_ext;

    localparam signed [33:0] MAX_32 =  34'sd2147483647;
    localparam signed [33:0] MIN_32 = -34'sd2147483648;

    always @(posedge clk or negedge rst_n) begin
        if (!rst_n) begin
            acc      <= 32'sd0;
            overflow <= 1'b0;
        end else if (clear_acc) begin
            acc      <= 32'sd0;
            overflow <= 1'b0;
        end else if (mac_en) begin
            if (sum_ext > MAX_32) begin
                acc      <= 32'sh7FFFFFFF;
                overflow <= 1'b1;
            end else if (sum_ext < MIN_32) begin
                acc      <= 32'sh80000000;
                overflow <= 1'b1;
            end else begin
                acc <= sum_ext[31:0];
            end
        end
    end
endmodule

tp4/verilog/fpga_tp4/src/tb_mac_unit.v
`timescale 1ns/1ps

module tb_mac_unit;

    reg clk, rst_n;
    reg signed [15:0] a, b;
    reg mac_en, clear_acc;
    wire signed [31:0] acc;
    wire overflow;

    mac_unit dut (
        .clk(clk), .rst_n(rst_n),
        .a(a), .b(b), .mac_en(mac_en), .clear_acc(clear_acc),
        .acc(acc), .overflow(overflow)
    );

    always #10 clk = ~clk;

    task do_mac(input signed [15:0] va, input signed [15:0] vb);
        begin
            a = va; b = vb; mac_en = 1'b1;
            @(posedge clk); #1;
            mac_en = 1'b0;
            @(posedge clk); #1;
        end
    endtask

    initial begin
        $dumpfile("tb_mac_unit.vcd");
        $dumpvars(0, tb_mac_unit);

        clk = 0; rst_n = 0; a = 0; b = 0; mac_en = 0; clear_acc = 0;
        repeat (2) @(posedge clk);
        rst_n = 1; #1;

        // Caso 1: 100 * 50 = 5000
        do_mac(100, 50);
        if (acc !== 32'sd5000) $display("FALHA Caso1: acc=%0d (esperado 5000)", acc);
        else $display("OK Caso1: MAC positivo simples, acc=%0d", acc);

        // Caso 2: soma com valor negativo: -100*50 = -5000 -> acc volta a 0
        do_mac(-100, 50);
        if (acc !== 32'sd0) $display("FALHA Caso2: acc=%0d (esperado 0)", acc);
        else $display("OK Caso2: MAC com operando negativo, acc=%0d", acc);

        // Caso 3: satura no maximo positivo (32767*32767 aplicado duas vezes)
        do_mac(32767, 32767);
        do_mac(32767, 32767);
        do_mac(32767, 32767);
        if (acc !== 32'sh7FFFFFFF || overflow !== 1'b1)
            $display("FALHA Caso3: acc=%0d overflow=%b", acc, overflow);
        else $display("OK Caso3: saturacao positiva detectada, acc=%0d overflow=%b", acc, overflow);

        // Caso 4: clear_acc reseta acumulador e flag de overflow
        clear_acc = 1'b1; @(posedge clk); #1; clear_acc = 1'b0; @(posedge clk); #1;
        if (acc !== 32'sd0 || overflow !== 1'b0)
            $display("FALHA Caso4: acc=%0d overflow=%b", acc, overflow);
        else $display("OK Caso4: clear_acc funcionando, acc=%0d overflow=%b", acc, overflow);

        // Caso 5: satura no minimo negativo apos reset
        do_mac(-32768, 32767);
        do_mac(-32768, 32767);
        do_mac(-32768, 32767);
        if (acc !== 32'sh80000000 || overflow !== 1'b1)
            $display("FALHA Caso5: acc=%0d overflow=%b", acc, overflow);
        else $display("OK Caso5: saturacao negativa detectada, acc=%0d overflow=%b", acc, overflow);

        // Caso 6: operacao normal apos novo clear
        clear_acc = 1'b1; @(posedge clk); #1; clear_acc = 1'b0; @(posedge clk); #1;
        do_mac(10, 10);
        if (acc !== 32'sd100 || overflow !== 1'b0)
            $display("FALHA Caso6: acc=%0d overflow=%b", acc, overflow);
        else $display("OK Caso6: operacao normal restaurada, acc=%0d overflow=%b", acc, overflow);

        #50;
        $display("Testbench concluido.");
        $finish;
    end
endmodule

tp4/verilog/fpga_tp4/src/tb_mac_unit.vcd
$date
	Sun Aug 30 16:44:06 2026
$end
$version
	Icarus Verilog
$end
$timescale
	1ps
$end
$scope module tb_mac_unit $end
$var wire 1 ! overflow $end
$var wire 32 " acc [31:0] $end
$var reg 16 # a [15:0] $end
$var reg 16 $ b [15:0] $end
$var reg 1 % clear_acc $end
$var reg 1 & clk $end
$var reg 1 ' mac_en $end
$var reg 1 ( rst_n $end
$scope module dut $end
$var wire 16 ) a [15:0] $end
$var wire 16 * b [15:0] $end
$var wire 1 % clear_acc $end
$var wire 1 & clk $end
$var wire 1 ' mac_en $end
$var wire 1 ( rst_n $end
$var wire 34 + sum_ext [33:0] $end
$var wire 33 , product_ext [32:0] $end
$var wire 32 - product [31:0] $end
$var wire 33 . acc_ext [32:0] $end
$var parameter 34 / MAX_32 $end
$var parameter 34 0 MIN_32 $end
$var reg 32 1 acc [31:0] $end
$var reg 1 ! overflow $end
$upscope $end
$scope task do_mac $end
$var reg 16 2 va [15:0] $end
$var reg 16 3 vb [15:0] $end
$upscope $end
$upscope $end
$enddefinitions $end
$comment Show the parameter values. $end
$dumpall
b1110000000000000000000000000000000 0
b1111111111111111111111111111111 /
$end
#0
$dumpvars
bx 3
bx 2
b0 1
b0 .
b0 -
b0 ,
b0 +
b0 *
b0 )
0(
0'
0&
0%
b0 $
b0 #
b0 "
0!
$end
#10000
1&
#20000
0&
#30000
1(
1&
#31000
1'
b1001110001000 +
b1001110001000 ,
b1001110001000 -
b110010 $
b110010 *
b1100100 #
b1100100 )
b110010 3
b1100100 2
#40000
0&
#50000
b10011100010000 +
b1001110001000 .
b1001110001000 "
b1001110001000 1
1&
#51000
0'
#60000
0&
#70000
1&
#71000
1'
b0 +
b111111111111111111110110001111000 ,
b11111111111111111110110001111000 -
b1111111110011100 #
b1111111110011100 )
b1111111110011100 2
#80000
0&
#90000
b1111111111111111111110110001111000 +
b0 .
b0 "
b0 1
1&
#91000
0'
#100000
0&
#110000
1&
#111000
1'
b111111111111111 $
b111111111111111 *
b111111111111110000000000000001 +
b111111111111110000000000000001 ,
b111111111111110000000000000001 -
b111111111111111 #
b111111111111111 )
b111111111111111 3
b111111111111111 2
#120000
0&
#130000
b1111111111111100000000000000010 +
b111111111111110000000000000001 .
b111111111111110000000000000001 "
b111111111111110000000000000001 1
1&
#131000
0'
#140000
0&
#150000
1&
#151000
1'
#160000
0&
#170000
b10111111111111010000000000000011 +
b1111111111111100000000000000010 .
b1111111111111100000000000000010 "
b1111111111111100000000000000010 1
1&
#171000
0'
#180000
0&
#190000
1&
#191000
1'
#200000
0&
#210000
1!
b10111111111111110000000000000000 +
b1111111111111111111111111111111 .
b1111111111111111111111111111111 "
b1111111111111111111111111111111 1
1&
#211000
0'
#220000
0&
#230000
1&
#231000
1%
#240000
0&
#250000
0!
b111111111111110000000000000001 +
b0 .
b0 "
b0 1
1&
#251000
0%
#260000
0&
#270000
1&
#271000
1'
b1111000000000000001000000000000000 +
b111000000000000001000000000000000 ,
b11000000000000001000000000000000 -
b1000000000000000 #
b1000000000000000 )
b1000000000000000 2
#280000
0&
#290000
b1110000000000000010000000000000000 +
b111000000000000001000000000000000 .
b11000000000000001000000000000000 "
b11000000000000001000000000000000 1
1&
#291000
0'
#300000
0&
#310000
1&
#311000
1'
#320000
0&
#330000
b1101000000000000011000000000000000 +
b110000000000000010000000000000000 .
b10000000000000010000000000000000 "
b10000000000000010000000000000000 1
1&
#331000
0'
#340000
0&
#350000
1&
#351000
1'
#360000
0&
#370000
1!
b1101000000000000001000000000000000 +
b110000000000000000000000000000000 .
b10000000000000000000000000000000 "
b10000000000000000000000000000000 1
1&
#371000
0'
#380000
0&
#390000
1&
#391000
1%
#400000
0&
#410000
0!
b1111000000000000001000000000000000 +
b0 .
b0 "
b0 1
1&
#411000
0%
#420000
0&
#430000
1&
#431000
1'
b1010 $
b1010 *
b1100100 +
b1100100 ,
b1100100 -
b1010 #
b1010 )
b1010 3
b1010 2
#440000
0&
#450000
b11001000 +
b1100100 .
b1100100 "
b1100100 1
1&
#451000
0'
