tp4/verilog/fpga_tp4/src/mac_unit.v
module mac_unit (
    input  wire               clk,
    input  wire               rst_n,
    input  wire signed [15:0] a,
    input  wire signed [15:0] b,
    input  wire               mac_en,
    input  wire               clear_acc,
    output reg  signed [31:0] acc,
    output reg                overflow
);
    wire signed [31:0] product = a * b;
    wire signed [32:0] acc_ext     = {acc[31], acc};
    wire signed [32:0] product_ext = {product[31], product};
    wire signed [33:0] sum_ext     = acc_ext + product_ext;

    localparam signed [33:0] MAX_32 =  34'sd2147483647;
    localparam signed [33:0] MIN_32 = -34'sd2147483648;

    always @(posedge clk or negedge rst_n) begin
        if (!rst_n) begin
            acc      <= 32'sd0;
            overflow <= 1'b0;
        end else if (clear_acc) begin
            acc      <= 32'sd0;
            overflow <= 1'b0;
        end else if (mac_en) begin
            if (sum_ext > MAX_32) begin
                acc      <= 32'sh7FFFFFFF;
                overflow <= 1'b1;
            end else if (sum_ext < MIN_32) begin
                acc      <= 32'sh80000000;
                overflow <= 1'b1;
            end else begin
                acc <= sum_ext[31:0];
            end
        end
    end
endmodule

tp4/verilog/fpga_tp4/src/sample_rom.v
module sample_rom (
    input  wire        clk,
    input  wire [5:0]  addr,
    output reg  signed [15:0] dout
);
    (* ram_style = "block" *)
    reg signed [15:0] mem [0:63];

    integer i;
    initial begin
        for (i = 0; i < 64; i = i + 1)
            mem[i] = 16'sd18000;
    end

    always @(posedge clk) dout <= mem[addr];
endmodule

tp4/verilog/fpga_tp4/src/coeff_rom.v
module coeff_rom (
    input  wire        clk,
    input  wire [5:0]  addr,
    output reg  signed [15:0] dout
);
    (* ram_style = "block" *)
    reg signed [15:0] mem [0:63];

    integer i;
    initial begin
        for (i = 0; i < 64; i = i + 1)
            mem[i] = 16'sd15000 + i * 100;
    end

    always @(posedge clk) dout <= mem[addr];
endmodule

tp4/verilog/fpga_tp4/src/mac_control.v
module mac_control (
    input  wire       clk,
    input  wire       rst_n,
    input  wire       step_pulse,
    input  wire       reset_pulse,
    output reg  [5:0] addr,
    output reg        mac_en,
    output reg        clear_acc
);
    localparam S_IDLE = 2'b00;
    localparam S_LOAD = 2'b01;
    localparam S_MAC  = 2'b10;

    reg [1:0] state;

    always @(posedge clk or negedge rst_n) begin
        if (!rst_n) begin
            state     <= S_IDLE;
            addr      <= 6'd0;
            mac_en    <= 1'b0;
            clear_acc <= 1'b0;
        end else begin
            mac_en    <= 1'b0;
            clear_acc <= 1'b0;

            case (state)
                S_IDLE: begin
                    if (reset_pulse) begin
                        addr      <= 6'd0;
                        clear_acc <= 1'b1;
                    end else if (step_pulse) begin
                        state <= S_LOAD;
                    end
                end

                S_LOAD: state <= S_MAC;

                S_MAC: begin
                    mac_en <= 1'b1;
                    addr   <= addr + 6'd1;
                    state  <= S_IDLE;
                end

                default: state <= S_IDLE;
            endcase
        end
    end
endmodule

tp4/verilog/fpga_tp4/src/tb_top_mac.v
`timescale 1ns/1ps

module tb_top_mac;

    reg clk, rst_n;
    reg step_pulse, reset_pulse;
    wire [5:0] addr;
    wire mac_en, clear_acc;

    mac_control u_ctrl (
        .clk(clk), .rst_n(rst_n),
        .step_pulse(step_pulse), .reset_pulse(reset_pulse),
        .addr(addr), .mac_en(mac_en), .clear_acc(clear_acc)
    );

    wire signed [15:0] coeff_dout, sample_dout;
    coeff_rom  u_coeff  (.clk(clk), .addr(addr), .dout(coeff_dout));
    sample_rom u_sample (.clk(clk), .addr(addr), .dout(sample_dout));

    wire signed [31:0] acc;
    wire overflow;

    mac_unit u_mac (
        .clk(clk), .rst_n(rst_n),
        .a(coeff_dout), .b(sample_dout),
        .mac_en(mac_en), .clear_acc(clear_acc),
        .acc(acc), .overflow(overflow)
    );

    always #10 clk = ~clk;

    task press_step;
        begin
            step_pulse = 1'b1; @(posedge clk); #1;
            step_pulse = 1'b0;
            repeat (3) @(posedge clk); #1;
        end
    endtask

    integer i;
    initial begin
        $dumpfile("tb_top_mac.vcd");
        $dumpvars(0, tb_top_mac);

        clk = 0; rst_n = 0; step_pulse = 0; reset_pulse = 0;
        repeat (2) @(posedge clk);
        rst_n = 1; #1;

        // Executa 8 passos consecutivos, lendo da BRAM (coeff/sample) via mac_control
        for (i = 0; i < 8; i = i + 1) press_step;

        $display("Apos 8 passos: addr=%0d acc=%0d overflow=%b", addr, acc, overflow);

        #50;
        $display("Testbench de integracao concluido.");
        $finish;
    end
endmodule

tp4/verilog/fpga_tp4/src/tb_top_mac.vcd
$date
	Sun Aug 30 16:49:09 2026
$end
$version
	Icarus Verilog
$end
$timescale
	1ps
$end
$scope module tb_top_mac $end
$var wire 16 ! sample_dout [15:0] $end
$var wire 1 " overflow $end
$var wire 1 # mac_en $end
$var wire 16 $ coeff_dout [15:0] $end
$var wire 1 % clear_acc $end
$var wire 6 & addr [5:0] $end
$var wire 32 ' acc [31:0] $end
$var reg 1 ( clk $end
$var reg 1 ) reset_pulse $end
$var reg 1 * rst_n $end
$var reg 1 + step_pulse $end
$var integer 32 , i [31:0] $end
$scope module u_coeff $end
$var wire 1 ( clk $end
$var wire 6 - addr [5:0] $end
$var reg 16 . dout [15:0] $end
$var integer 32 / i [31:0] $end
$upscope $end
$scope module u_ctrl $end
$var wire 1 ( clk $end
$var wire 1 ) reset_pulse $end
$var wire 1 * rst_n $end
$var wire 1 + step_pulse $end
$var parameter 2 0 S_IDLE $end
$var parameter 2 1 S_LOAD $end
$var parameter 2 2 S_MAC $end
$var reg 6 3 addr [5:0] $end
$var reg 1 % clear_acc $end
$var reg 1 # mac_en $end
$var reg 2 4 state [1:0] $end
$upscope $end
$scope module u_mac $end
$var wire 16 5 a [15:0] $end
$var wire 1 % clear_acc $end
$var wire 1 ( clk $end
$var wire 1 # mac_en $end
$var wire 1 * rst_n $end
$var wire 34 6 sum_ext [33:0] $end
$var wire 33 7 product_ext [32:0] $end
$var wire 32 8 product [31:0] $end
$var wire 16 9 b [15:0] $end
$var wire 33 : acc_ext [32:0] $end
$var parameter 34 ; MAX_32 $end
$var parameter 34 < MIN_32 $end
$var reg 32 = acc [31:0] $end
$var reg 1 " overflow $end
$upscope $end
$scope module u_sample $end
$var wire 6 > addr [5:0] $end
$var wire 1 ( clk $end
$var reg 16 ? dout [15:0] $end
$var integer 32 @ i [31:0] $end
$upscope $end
$scope task press_step $end
$upscope $end
$upscope $end
$enddefinitions $end
$comment Show the parameter values. $end
$dumpall
b1110000000000000000000000000000000 <
b1111111111111111111111111111111 ;
b10 2
b1 1
b0 0
$end
#0
$dumpvars
b1000000 @
bx ?
b0 >
b0 =
b0 :
bx 9
bx 8
bx 7
bx 6
bx 5
b0 4
b0 3
b1000000 /
bx .
b0 -
bx ,
0+
0*
0)
0(
b0 '
b0 &
0%
bx $
0#
0"
bx !
$end
#10000
b100011110000110100011000000000 6
b100011110000110100011000000000 7
b100011110000110100011000000000 8
b111010100110000 $
b111010100110000 .
b111010100110000 5
b100111000100000 !
b100111000100000 9
b100111000100000 ?
1(
#20000
0(
#30000
1*
1(
#31000
1+
b0 ,
#40000
0(
#50000
b1 4
1(
#51000
0+
#60000
0(
#70000
b10 4
1(
#80000
0(
#90000
b0 4
b1 &
b1 -
b1 3
b1 >
1#
1(
#100000
0(
#110000
0#
b100011110000110100011000000000 :
b100011110000110100011000000000 '
b100011110000110100011000000000 =
b1011100110110000 !
b1011100110110000 9
b1011100110110000 ?
b1000001101101111011101100000000 6
b11101111101000111010100000000 7
b11101111101000111010100000000 8
b1001001011110000 $
b1001001011110000 .
b1001001011110000 5
1(
#111000
1+
b1 ,
#120000
0(
#130000
b1 4
1(
#131000
0+
#140000
0(
#150000
b10 4
1(
#160000
0(
#170000
b0 4
b10 &
b10 -
b10 3
b10 >
1#
1(
#180000
0(
#190000
0#
b1000001101101111011101100000000 :
b1000001101101111011101100000000 '
b1000001101101111011101100000000 =
b100001101111101110101010000000 6
b111100000000001110010111110000000 7
b11100000000001110010111110000000 8
b111010001101000 $
b111010001101000 .
b111010001101000 5
1(
#191000
1+
b10 ,
#200000
0(
#210000
b1 4
1(
#211000
0+
#220000
0(
#230000
b10 4
1(
#240000
0(
#250000
b0 4
b11 &
b11 -
b11 3
b11 >
1#
1(
#260000
0(
#270000
0#
b100001101111101110101010000000 :
b100001101111101110101010000000 '
b100001101111101110101010000000 =
b100111000100000 !
b100111000100000 9
b100111000100000 ?
b101001110011110010000000 6
b111011110111010000101001000000000 7
b11011110111010000101001000000000 8
b1001001110010000 $
b1001001110010000 .
b1001001110010000 5
1(
#271000
1+
b11 ,
#280000
0(
#290000
b1 4
1(
#291000
0+
#300000
0(
#310000
b10 4
1(
#320000
0(
#330000
b0 4
b100 &
b100 -
b100 3
b100 >
1#
1(
#340000
0(
#350000
0#
b101001110011110010000000 :
b101001110011110010000000 '
b101001110011110010000000 =
b1011100110110000 !
b1011100110110000 9
b1011100110110000 ?
b1111100000111001010101101010000000 6
b111100000001111100001111000000000 7
b11100000001111100001111000000000 8
b111001110100000 $
b111001110100000 .
b111001110100000 5
1(
#351000
1+
b100 ,
#360000
0(
#370000
b1 4
1(
#371000
0+
#380000
0(
#390000
b10 4
1(
#400000
0(
#410000
b0 4
b101 &
b101 -
b101 3
b101 >
1#
1(
#420000
0(
#430000
0#
b111100000111001010101101010000000 :
b11100000111001010101101010000000 '
b11100000111001010101101010000000 =
b1111111110100000011110101110000000 6
b11101100111001001000100000000 7
b11101100111001001000100000000 8
b1001010000110000 $
b1001010000110000 .
b1001010000110000 5
1(
#431000
1+
b101 ,
#440000
0(
#450000
b1 4
1(
#451000
0+
#460000
0(
#470000
b10 4
1(
#480000
0(
#490000
b0 4
b110 &
b110 -
b110 3
b110 >
1#
1(
#500000
0(
#510000
0#
b111111110100000011110101110000000 :
b11111110100000011110101110000000 '
b11111110100000011110101110000000 =
b100111000100000 !
b100111000100000 9
b100111000100000 ?
b100001100011100001011010000000 6
b100011000011000010101100000000 7
b100011000011000010101100000000 8
b111001011011000 $
b111001011011000 .
b111001011011000 5
1(
#511000
1+
b110 ,
#520000
0(
#530000
b1 4
1(
#531000
0+
#540000
0(
#550000
b10 4
1(
#560000
0(
#570000
b0 4
b111 &
b111 -
b111 3
b111 >
1#
1(
#580000
0(
#590000
0#
b100001100011100001011010000000 :
b100001100011100001011010000000 '
b100001100011100001011010000000 =
b1011100110110000 !
b1011100110110000 9
b1011100110110000 ?
b111110111111101011010110000000 6
b11101011100001001111100000000 7
b11101011100001001111100000000 8
b1001010011010000 $
b1001010011010000 .
b1001010011010000 5
1(
#591000
1+
b111 ,
#600000
0(
#610000
b1 4
1(
#611000
0+
#620000
0(
#630000
b10 4
1(
#640000
0(
#650000
b0 4
b1000 &
b1000 -
b1000 3
b1000 >
1#
1(
#660000
0(
#670000
0#
b111110111111101011010110000000 :
b111110111111101011010110000000 '
b111110111111101011010110000000 =
b11111101010101011000010000000 6
b111100000101010111111101100000000 7
b11100000101010111111101100000000 8
b111001000010000 $
b111001000010000 .
b111001000010000 5
1(
#671000
b1000 ,
