tp5/verilog_tp5/fpga_tp5/src/mac_unit.v
module mac_unit #(
    parameter FRAC_BITS = 8
)(
    input  wire               clk,
    input  wire               rst_n,
    input  wire               oe,
    input  wire signed [15:0] a,
    input  wire signed [15:0] b,
    input  wire               mac_en,
    input  wire               clear_acc,
    output reg  signed [31:0] acc,
    output reg                overflow,
    output wire signed [15:0] acc_q88
);
    wire signed [31:0] product = a * b;

    wire signed [32:0] sum_ext =
        {acc[31], acc} + {product[31], product};

    localparam signed [33:0] MAX_32 =  34'sd2147483647;
    localparam signed [33:0] MIN_32 = -34'sd2147483648;

    always @(posedge clk or negedge rst_n) begin
        if (!rst_n) begin
            acc      <= 32'sd0;
            overflow <= 1'b0;
        end else if (!oe) begin
        end else if (clear_acc) begin
            acc      <= 32'sd0;
            overflow <= 1'b0;
        end else if (mac_en) begin
            if (sum_ext > MAX_32) begin
                acc      <= 32'sh7FFFFFFF;
                overflow <= 1'b1;
            end else if (sum_ext < MIN_32) begin
                acc      <= 32'sh80000000;
                overflow <= 1'b1;
            end else begin
                acc      <= sum_ext[31:0];
            end
        end
    end

    assign acc_q88 = acc[31:16];

endmodule

tp5/verilog_tp5/fpga_tp5/src/tb_mac_unit_v2.v
`timescale 1ns/1ps
module tb_mac_unit_v2;

    reg clk, rst_n, oe, mac_en, clear_acc;
    reg signed [15:0] a, b;
    wire signed [31:0] acc;
    wire overflow;
    wire signed [15:0] acc_q88;

    mac_unit #(.FRAC_BITS(8)) dut (
        .clk(clk), .rst_n(rst_n), .oe(oe),
        .a(a), .b(b), .mac_en(mac_en), .clear_acc(clear_acc),
        .acc(acc), .overflow(overflow), .acc_q88(acc_q88)
    );

    always #10 clk = ~clk;

    task do_mac(input signed [15:0] va, input signed [15:0] vb);
        begin
            a = va; b = vb; mac_en = 1;
            @(posedge clk); #1;
            mac_en = 0;
            @(posedge clk); #1;
        end
    endtask

    task do_clear;
        begin
            clear_acc = 1; @(posedge clk); #1;
            clear_acc = 0; @(posedge clk); #1;
        end
    endtask

    initial begin
        $dumpfile("tb_mac_unit_v2.vcd");
        $dumpvars(0, tb_mac_unit_v2);

        clk=0; rst_n=0; oe=1; mac_en=0; clear_acc=0; a=0; b=0;
        repeat(2) @(posedge clk);
        rst_n = 1; #1;

        do_mac(0, 32767);
        if (acc !== 0)
            $display("FALHA Caso1: acc=%0d", acc);
        else $display("OK Caso1: zero preservado, acc=%0d", acc);

        do_clear;
        do_mac(256, 256);
        if (acc !== 32'd65536)
            $display("FALHA Caso2: acc=%0d (esperado 65536)", acc);
        else $display("OK Caso2: Q8.8 1.0*1.0=65536 (acc_q88=%0d)", acc_q88);

        do_clear;
        do_mac(32767, 32767);
        do_mac(32767, 32767);
        do_mac(32767, 32767);
        if (acc !== 32'sh7FFFFFFF || overflow !== 1)
            $display("FALHA Caso3: acc=%0d overflow=%b", acc, overflow);
        else $display("OK Caso3: saturacao positiva no limite, acc=%0d", acc);

        do_clear;
        do_mac(100, 100);
        oe = 0;
        do_mac(200, 200);
        oe = 1;
        if (acc !== 32'sd10000)
            $display("FALHA Caso4: acc=%0d (esperado 10000, OE deveria congelar)", acc);
        else $display("OK Caso4: OE=0 congelou saida, acc=%0d", acc);

        do_clear;
        do_mac(10, 20);
        if (acc !== 32'sd200 || overflow !== 0)
            $display("FALHA Caso5: acc=%0d overflow=%b", acc, overflow);
        else $display("OK Caso5: operacao normal apos saturacao+clear, acc=%0d", acc);

        do_clear;
        do_mac(-32768, 32767);
        do_mac(-32768, 32767);
        do_mac(-32768, 32767);
        if (acc !== 32'sh80000000 || overflow !== 1)
            $display("FALHA Caso6: acc=%0d overflow=%b", acc, overflow);
        else $display("OK Caso6: saturacao negativa, acc=%0d", acc);

        #50;
        $display("Testbench v2 concluido.");
        $finish;
    end
endmodule

tp5/verilog_tp5/fpga_tp5/src/tb_mac_unit_v2.vcd
$date
	Wed Sep 09 20:28:23 2026
$end
$version
	Icarus Verilog
$end
$timescale
	1ps
$end
$scope module tb_mac_unit_v2 $end
$var wire 1 ! overflow $end
$var wire 16 " acc_q88 [15:0] $end
$var wire 32 # acc [31:0] $end
$var reg 16 $ a [15:0] $end
$var reg 16 % b [15:0] $end
$var reg 1 & clear_acc $end
$var reg 1 ' clk $end
$var reg 1 ( mac_en $end
$var reg 1 ) oe $end
$var reg 1 * rst_n $end
$scope module dut $end
$var wire 16 + a [15:0] $end
$var wire 16 , b [15:0] $end
$var wire 1 & clear_acc $end
$var wire 1 ' clk $end
$var wire 1 ( mac_en $end
$var wire 1 ) oe $end
$var wire 1 * rst_n $end
$var wire 33 - sum_ext [32:0] $end
$var wire 32 . product [31:0] $end
$var wire 16 / acc_q88 [15:0] $end
$var parameter 32 0 FRAC_BITS $end
$var parameter 34 1 MAX_32 $end
$var parameter 34 2 MIN_32 $end
$var reg 32 3 acc [31:0] $end
$var reg 1 ! overflow $end
$upscope $end
$scope task do_clear $end
$upscope $end
$scope task do_mac $end
$var reg 16 4 va [15:0] $end
$var reg 16 5 vb [15:0] $end
$upscope $end
$upscope $end
$enddefinitions $end
$comment Show the parameter values. $end
$dumpall
b1110000000000000000000000000000000 2
b1111111111111111111111111111111 1
b1000 0
$end
#0
$dumpvars
bx 5
bx 4
b0 3
b0 /
b0 .
b0 -
b0 ,
b0 +
0*
1)
0(
0'
0&
b0 %
b0 $
b0 #
b0 "
0!
$end
#10000
1'
#20000
0'
#30000
1*
1'
#31000
1(
b111111111111111 %
b111111111111111 ,
b111111111111111 5
b0 4
#40000
0'
#50000
1'
#51000
0(
#60000
0'
#70000
1'
#71000
1&
#80000
0'
#90000
1'
#91000
0&
#100000
0'
#110000
1'
#111000
1(
b100000000 %
b100000000 ,
b10000000000000000 -
b10000000000000000 .
b100000000 $
b100000000 +
b100000000 5
b100000000 4
#120000
0'
#130000
b1 "
b1 /
b100000000000000000 -
b10000000000000000 #
b10000000000000000 3
1'
#131000
0(
#140000
0'
#150000
1'
#151000
1&
#160000
0'
#170000
b0 "
b0 /
b10000000000000000 -
b0 #
b0 3
1'
#171000
0&
#180000
0'
#190000
1'
#191000
1(
b111111111111111 %
b111111111111111 ,
b111111111111110000000000000001 -
b111111111111110000000000000001 .
b111111111111111 $
b111111111111111 +
b111111111111111 5
b111111111111111 4
#200000
0'
#210000
b11111111111111 "
b11111111111111 /
b1111111111111100000000000000010 -
b111111111111110000000000000001 #
b111111111111110000000000000001 3
1'
#211000
0(
#220000
0'
#230000
1'
#231000
1(
#240000
0'
#250000
b111111111111110 "
b111111111111110 /
b10111111111111010000000000000011 -
b1111111111111100000000000000010 #
b1111111111111100000000000000010 3
1'
#251000
0(
#260000
0'
#270000
1'
#271000
1(
#280000
0'
#290000
b111111111111111 "
b111111111111111 /
1!
b10111111111111110000000000000000 -
b1111111111111111111111111111111 #
b1111111111111111111111111111111 3
1'
#291000
0(
#300000
0'
#310000
1'
#311000
1&
#320000
0'
#330000
b0 "
b0 /
0!
b111111111111110000000000000001 -
b0 #
b0 3
1'
#331000
0&
#340000
0'
#350000
1'
#351000
1(
b1100100 %
b1100100 ,
b10011100010000 -
b10011100010000 .
b1100100 $
b1100100 +
b1100100 5
b1100100 4
#360000
0'
#370000
b100111000100000 -
b10011100010000 #
b10011100010000 3
1'
#371000
0(
#380000
0'
#390000
1'
#391000
1(
b11001000 %
b11001000 ,
b1100001101010000 -
b1001110001000000 .
b11001000 $
b11001000 +
b11001000 5
b11001000 4
0)
#400000
0'
#410000
1'
#411000
0(
#420000
0'
#430000
1'
#431000
1&
1)
#440000
0'
#450000
b1001110001000000 -
b0 #
b0 3
1'
#451000
0&
#460000
0'
#470000
1'
#471000
1(
b10100 %
b10100 ,
b11001000 -
b11001000 .
b1010 $
b1010 +
b10100 5
b1010 4
#480000
0'
#490000
b110010000 -
b11001000 #
b11001000 3
1'
#491000
0(
#500000
0'
#510000
1'
#511000
1&
#520000
0'
#530000
b11001000 -
b0 #
b0 3
1'
#531000
0&
#540000
0'
#550000
1'
#551000
1(
b111111111111111 %
b111111111111111 ,
b111000000000000001000000000000000 -
b11000000000000001000000000000000 .
b1000000000000000 $
b1000000000000000 +
b111111111111111 5
b1000000000000000 4
#560000
0'
#570000
b1100000000000000 "
b1100000000000000 /
b110000000000000010000000000000000 -
b11000000000000001000000000000000 #
b11000000000000001000000000000000 3
1'
#571000
0(
#580000
0'
#590000
1'
#591000
1(
#600000
0'
#610000
b1000000000000001 "
b1000000000000001 /
b101000000000000011000000000000000 -
b10000000000000010000000000000000 #
b10000000000000010000000000000000 3
1'
#611000
0(
#620000
0'
#630000
1'
#631000
1(
#640000
0'
#650000
b1000000000000000 "
b1000000000000000 /
1!
b101000000000000001000000000000000 -
b10000000000000000000000000000000 #
b10000000000000000000000000000000 3
1'
#651000
0(
