tp3/verilog/tp3-verilog/src/fsm_control.v
module fsm_control #(
    parameter STABLE_CYCLES = 3
)(
    input  wire       clk,
    input  wire       rst_n,
    input  wire       cmd_trigger_sync,
    input  wire [1:0] cmd_data_sync,
    output wire       busy,
    output wire       error_flag,   // pulso combinacional, so em S_ERROR
    output wire       error_latch,  // persistente, para exibicao no LED
    output wire [1:0] led_result
);

    // ---- Estados ----
    localparam S_IDLE         = 3'b000;
    localparam S_SYNC_CAPTURE = 3'b001;
    localparam S_VALIDATE     = 3'b010;
    localparam S_EXECUTE      = 3'b011;
    localparam S_ERROR        = 3'b100;
    localparam S_WAIT_RELEASE = 3'b101;

    reg [2:0] state, next_state;
    reg [3:0] stable_cnt;
    reg [1:0] cmd_reg;
    reg [1:0] led_result_reg;
    reg       error_latch_reg;

    // ---------- LOGICA DE TRANSICAO (sequencial) ----------
    always @(posedge clk or negedge rst_n) begin
        if (!rst_n) state <= S_IDLE;
        else        state <= next_state;
    end

    always @(*) begin
        next_state = state;
        case (state)
            S_IDLE:
                if (cmd_trigger_sync) next_state = S_SYNC_CAPTURE;

            S_SYNC_CAPTURE:
                if (!cmd_trigger_sync)                   next_state = S_IDLE;
                else if (stable_cnt >= STABLE_CYCLES-1)   next_state = S_VALIDATE;

            S_VALIDATE:
                next_state = (cmd_reg == 2'b11) ? S_ERROR : S_EXECUTE;

            S_EXECUTE:
                next_state = S_WAIT_RELEASE;

            S_ERROR:
                next_state = S_WAIT_RELEASE;

            S_WAIT_RELEASE:
                if (!cmd_trigger_sync) next_state = S_IDLE;

            default: next_state = S_IDLE;
        endcase
    end

    // ---------- DATAPATH ----------
    always @(posedge clk or negedge rst_n) begin
        if (!rst_n) stable_cnt <= 4'd0;
        else if (state == S_SYNC_CAPTURE) stable_cnt <= stable_cnt + 4'd1;
        else stable_cnt <= 4'd0;
    end

    always @(posedge clk or negedge rst_n) begin
        if (!rst_n) cmd_reg <= 2'b00;
        else if (state == S_SYNC_CAPTURE) cmd_reg <= cmd_data_sync;
    end

    always @(posedge clk or negedge rst_n) begin
        if (!rst_n) led_result_reg <= 2'b00;
        else if (state == S_EXECUTE) led_result_reg <= cmd_reg;
    end

    always @(posedge clk or negedge rst_n) begin
        if (!rst_n) error_latch_reg <= 1'b0;
        else if (state == S_ERROR)   error_latch_reg <= 1'b1;
        else if (state == S_EXECUTE) error_latch_reg <= 1'b0;
    end

    // ---------- LOGICA DE SAIDA (combinacional) ----------
    assign busy        = (state != S_IDLE);
    assign error_flag  = (state == S_ERROR);
    assign error_latch = error_latch_reg;
    assign led_result  = led_result_reg;

endmodule

tp3/verilog/tp3-verilog/src/tb_fsm_control.v
`timescale 1ns/1ps

module tb_fsm_control;

    reg clk, rst_n;
    reg cmd_trigger_sync;
    reg [1:0] cmd_data_sync;
    wire busy, error_flag, error_latch;
    wire [1:0] led_result;

    fsm_control #(.STABLE_CYCLES(3)) dut (
        .clk(clk), .rst_n(rst_n),
        .cmd_trigger_sync(cmd_trigger_sync),
        .cmd_data_sync(cmd_data_sync),
        .busy(busy), .error_flag(error_flag), .error_latch(error_latch),
        .led_result(led_result)
    );

    always #10 clk = ~clk;

    task send_command(input [1:0] cmd, input integer hold_cycles);
        integer i;
        begin
            cmd_data_sync    = cmd;
            cmd_trigger_sync = 1'b1;
            for (i = 0; i < hold_cycles; i = i + 1) @(posedge clk);
            cmd_trigger_sync = 1'b0;
            cmd_data_sync    = 2'b00;
            @(posedge clk); @(posedge clk);
        end
    endtask

    initial begin
        $dumpfile("tb_fsm_control.vcd");
        $dumpvars(0, tb_fsm_control);

        clk = 0; rst_n = 0;
        cmd_trigger_sync = 0; cmd_data_sync = 2'b00;
        repeat (4) @(posedge clk);
        rst_n = 1;

        // Caso 1: LED_ON
        send_command(2'b01, 5); #5;
        if (led_result !== 2'b01 || error_flag !== 1'b0)
            $display("FALHA Caso1: led_result=%b error=%b", led_result, error_flag);
        else $display("OK Caso1: LED_ON aplicado corretamente");

        // Caso 2: STATUS
        send_command(2'b10, 5); #5;
        if (led_result !== 2'b10) $display("FALHA Caso2: led_result=%b", led_result);
        else $display("OK Caso2: STATUS aplicado corretamente");

        // Caso 3: LED_OFF
        send_command(2'b00, 5); #5;
        if (led_result !== 2'b00) $display("FALHA Caso3: led_result=%b", led_result);
        else $display("OK Caso3: LED_OFF aplicado corretamente");

        // Caso 4: comando invalido
        send_command(2'b11, 5); #5;
        if (dut.error_latch !== 1'b1)
            $display("FALHA Caso4: error_latch=%b", dut.error_latch);
        else $display("OK Caso4: erro detectado para comando 11");

        // Caso 5: glitch (trigger sobe e cai antes de STABLE_CYCLES)
        cmd_data_sync = 2'b01; cmd_trigger_sync = 1'b1;
        @(posedge clk);
        cmd_trigger_sync = 1'b0; cmd_data_sync = 2'b00;
        repeat (3) @(posedge clk);
        if (dut.state !== 3'b000)
            $display("FALHA Caso5: state=%b (esperado IDLE)", dut.state);
        else $display("OK Caso5: glitch ignorado, retorno a IDLE");

        // Caso 6: recuperacao apos erro
        send_command(2'b01, 5); #5;
        if (dut.error_latch !== 1'b0 || led_result !== 2'b01)
            $display("FALHA Caso6: error_latch=%b led_result=%b", dut.error_latch, led_result);
        else $display("OK Caso6: erro limpo apos novo comando valido");

        #50;
        $display("Testbench concluido.");
        $finish;
    end
endmodule

tp3/verilog/tp3-verilog/src/tb_fsm_control.vcd
$date
	Tue Aug 04 20:56:48 2026
$end
$version
	Icarus Verilog
$end
$timescale
	1ps
$end
$scope module tb_fsm_control $end
$var wire 2 ! led_result [1:0] $end
$var wire 1 " error_latch $end
$var wire 1 # error_flag $end
$var wire 1 $ busy $end
$var reg 1 % clk $end
$var reg 2 & cmd_data_sync [1:0] $end
$var reg 1 ' cmd_trigger_sync $end
$var reg 1 ( rst_n $end
$scope module dut $end
$var wire 1 % clk $end
$var wire 2 ) cmd_data_sync [1:0] $end
$var wire 1 ' cmd_trigger_sync $end
$var wire 1 " error_latch $end
$var wire 2 * led_result [1:0] $end
$var wire 1 ( rst_n $end
$var wire 1 # error_flag $end
$var wire 1 $ busy $end
$var parameter 32 + STABLE_CYCLES $end
$var parameter 3 , S_ERROR $end
$var parameter 3 - S_EXECUTE $end
$var parameter 3 . S_IDLE $end
$var parameter 3 / S_SYNC_CAPTURE $end
$var parameter 3 0 S_VALIDATE $end
$var parameter 3 1 S_WAIT_RELEASE $end
$var reg 2 2 cmd_reg [1:0] $end
$var reg 1 3 error_latch_reg $end
$var reg 2 4 led_result_reg [1:0] $end
$var reg 3 5 next_state [2:0] $end
$var reg 4 6 stable_cnt [3:0] $end
$var reg 3 7 state [2:0] $end
$upscope $end
$scope task send_command $end
$var reg 2 8 cmd [1:0] $end
$var integer 32 9 hold_cycles [31:0] $end
$var integer 32 : i [31:0] $end
$upscope $end
$upscope $end
$enddefinitions $end
$comment Show the parameter values. $end
$dumpall
b101 1
b10 0
b1 /
b0 .
b11 -
b100 ,
b11 +
$end
#0
$dumpvars
bx :
bx 9
bx 8
b0 7
b0 6
b0 5
b0 4
03
b0 2
b0 *
b0 )
0(
0'
b0 &
0%
0$
0#
0"
b0 !
$end
#10000
1%
#20000
0%
#30000
1%
#40000
0%
#50000
1%
#60000
0%
#70000
b1 5
b0 :
1'
b1 &
b1 )
b101 9
b1 8
1(
1%
#80000
0%
#90000
1$
b1 7
b1 :
1%
#100000
0%
#110000
b1 6
b1 2
b10 :
1%
#120000
0%
#130000
b10 5
b10 6
b11 :
1%
#140000
0%
#150000
b11 5
b10 7
b11 6
b100 :
1%
#160000
0%
#170000
b0 6
b11 7
b101 5
b0 &
b0 )
0'
b101 :
1%
#180000
0%
#190000
b0 5
b101 7
b1 !
b1 *
b1 4
1%
#200000
0%
#210000
0$
b0 7
1%
#215000
b1 5
b0 :
1'
b10 &
b10 )
b10 8
#220000
0%
#230000
1$
b1 7
b1 :
1%
#240000
0%
#250000
b10 2
b1 6
b10 :
1%
#260000
0%
#270000
b10 5
b10 6
b11 :
1%
#280000
0%
#290000
b11 5
b11 6
b10 7
b100 :
1%
#300000
0%
#310000
b11 7
b0 6
b101 5
b0 &
b0 )
0'
b101 :
1%
#320000
0%
#330000
b0 5
b10 !
b10 *
b10 4
b101 7
1%
#340000
0%
#350000
0$
b0 7
1%
#355000
b1 5
b0 :
1'
b0 8
#360000
0%
#370000
1$
b1 7
b1 :
1%
#380000
0%
#390000
b1 6
b0 2
b10 :
1%
#400000
0%
#410000
b10 5
b10 6
b11 :
1%
#420000
0%
#430000
b11 5
b10 7
b11 6
b100 :
1%
#440000
0%
#450000
b0 6
b11 7
b101 5
0'
b101 :
1%
#460000
0%
#470000
b0 5
b101 7
b0 !
b0 *
b0 4
1%
#480000
0%
#490000
0$
b0 7
1%
#495000
b1 5
b0 :
1'
b11 &
b11 )
b11 8
#500000
0%
#510000
1$
b1 7
b1 :
1%
#520000
0%
#530000
b11 2
b1 6
b10 :
1%
#540000
0%
#550000
b10 5
b10 6
b11 :
1%
#560000
0%
#570000
b100 5
b11 6
b10 7
b100 :
1%
#580000
0%
#590000
1#
b100 7
b0 6
b101 5
b0 &
b0 )
0'
b101 :
1%
#600000
0%
#610000
b0 5
1"
13
0#
b101 7
1%
#620000
0%
#630000
0$
b0 7
1%
#635000
b1 5
1'
b1 &
b1 )
#640000
0%
#650000
1$
b1 7
b0 5
b0 &
b0 )
0'
1%
#660000
0%
#670000
0$
b0 7
b1 6
b0 2
1%
#680000
0%
#690000
b0 6
1%
#700000
0%
#710000
b1 5
b0 :
1'
b1 &
b1 )
b1 8
1%
#720000
0%
#730000
1$
b1 7
b1 :
1%
#740000
0%
#750000
b1 6
b1 2
b10 :
1%
#760000
0%
#770000
b10 5
b10 6
b11 :
1%
#780000
0%
#790000
b11 5
b10 7
b11 6
b100 :
1%
#800000
0%
#810000
b0 6
b11 7
b101 5
b0 &
b0 )
0'
b101 :
1%
#820000
0%
#830000
b0 5
b101 7
b1 !
b1 *
b1 4
0"
03
1%
#840000
0%
#850000
0$
b0 7
1%
